switlm/__init__.py
switlm/config.py
switlm/dataset.py
switlm/generator.py
switlm/gguf_converter.py
switlm/model.py
switlm/trainer.py
switlm-0.1.1.dist-info/licenses/LICENSE
switlm-0.1.1.dist-info/METADATA
switlm-0.1.1.dist-info/WHEEL
switlm-0.1.1.dist-info/top_level.txt
switlm-0.1.1.dist-info/RECORD
