Metadata-Version: 2.4
Name: switlm
Version: 0.1.1
Summary: A simple yet powerful library to create and train custom LLMs with GGUF export
Home-page: https://github.com/Avijit0001/switlm
Author: Avijit Paul
Author-email: avijit.paul0001@gmail.com
Classifier: Development Status :: 3 - Alpha
Classifier: Intended Audience :: Developers
Classifier: Intended Audience :: Science/Research
Classifier: License :: OSI Approved :: MIT License
Classifier: Programming Language :: Python :: 3
Classifier: Programming Language :: Python :: 3.8
Classifier: Programming Language :: Python :: 3.9
Classifier: Programming Language :: Python :: 3.10
Classifier: Programming Language :: Python :: 3.11
Classifier: Programming Language :: Python :: 3.12
Classifier: Programming Language :: Python :: 3.13
Classifier: Topic :: Scientific/Engineering :: Artificial Intelligence
Requires-Python: >=3.8
License-File: LICENSE
Requires-Dist: torch>=2.0.0
Requires-Dist: transformers>=4.30.0
Requires-Dist: datasets>=2.12.0
Requires-Dist: tqdm>=4.65.0
Requires-Dist: numpy>=1.24.0
Requires-Dist: wandb>=0.15.0
Provides-Extra: dev
Requires-Dist: pytest>=7.3.0; extra == "dev"
Requires-Dist: black>=23.3.0; extra == "dev"
Requires-Dist: flake8>=6.0.0; extra == "dev"
Dynamic: author
Dynamic: author-email
Dynamic: classifier
Dynamic: description
Dynamic: description-content-type
Dynamic: home-page
Dynamic: license-file
Dynamic: provides-extra
Dynamic: requires-dist
Dynamic: requires-python
Dynamic: summary
